README.rst
setup.py
multiJump/__init__.py
multiJump/multiJump.py
multiJump.egg-info/PKG-INFO
multiJump.egg-info/SOURCES.txt
multiJump.egg-info/dependency_links.txt
multiJump.egg-info/requires.txt
multiJump.egg-info/top_level.txt