Metadata-Version: 1.1
Name: multiJump
Version: 0.0.5
Summary: multiple Jump IP do something
Home-page: https://github.com/seqyuan/multiJump/wiki
Author: seqyuan
Author-email: seqyuan@gmail.com
License: MIT
Download-URL: https://codeload.github.com/seqyuan/multiJump/zip/master
Platform: UNKNOWN
